{
    "name": "Blaze The Cat",
    "description": "A fiery feline friend",
    "headTexture": "eyJ0ZXh0dXJlcyI6eyJTS0lOIjp7InVybCI6Imh0dHA6Ly90ZXh0dXJlcy5taW5lY3JhZnQubmV0L3RleHR1cmUvYjJjODM0MWRmMGI4MmQzNzYxMjBjZjMyMzMyYTI0MjNmMzBhZmRlYTU5Njg5ZjA4Y2U2ODI4OGJiMWRhOGZkZCJ9fX0=",
    "armor": [
        "leather",
        "iron",
        "leather"
    ],
    "color_scheme": [
        "purple",
        "hot_pink",
        "orange"
    ],
    "effects": [
        "speed",
        "strength",
        {
            "name": "jump_boost",
            "amplifier": 2
        }
    ],
    "ability_slots": [
        {
            "name": "Blazing Fury",
            "description": "Ignites Enemies",
            "action_slots": [
                "r-click",
                "shift-click",
                "f-press",
                "shift-f-press",
                "q-press",
                "shift-q-press"
            ],
            "cooldown": [1.0, 2.0, 3.0, 4.0, 5.0, 6.0]
        },
        [
            {
                "name": "Fire Dash",
                "description": "Quickly dashes forward leaving a trail of fire",
                "sneakCooldown": 5.0,
                "cooldown": 2.5
            },
            {
                "name": "Inferno Shield",
                "description": "Surrounds self with a barrier of flames, burned attackers",
                "sneakCooldown": 1.5,
                "cooldown": 1.5
            },
            {
                "name": "Fireball Barrage",
                "description": "Launches a barrage of fireballs that explode on impact",
                "cooldown": 3.0
            },
            {
                "name": "Fiery Frenzy",
                "description": "Increases speed and strength for a short duration",
                "sneakCooldown": 10.0
            }
        ],
        {
            "name": "Ember Flare",
            "description": "Launches fiery projectiles that explode on impact",
            "action_slots": [
                "r-click",
                "q-press"
            ],
            "cooldown": 2.0
        },
        [
            {
                "name": "Fire Blitz",
                "description": "Quickly dashes forward in flame"
            },
            {
                "name": "Inferno Maze",
                "description": "Create a maze of flames, Burning attackers",
                "sneakCooldown": 2.0
            }
        ]
    ],
    "crafting_recipe": {
        "minecraft:blaze_rod": 32,
        "minecraft:ender_eye": 2,
        "minecraft:gunpowder": 64,
        "minecraft:potion": {
            "potion_contents": "fire_resistance",
            "count": 1
        },
        "minecraft:fire_charge": 32,
        "minecraft:kelp": 32,
        "minecraft:cooked_cod": 10,
        "minecraft:cooked_salmon": 10,
        "minecraft:tropical_fish": 10,
        "minecraft:pufferfish": 1
    }
}
